{
  "residents": [
    {
      "id": "b1972cad-1526-4557-a443-09289488dcbf",
      "name": "Nina",
      "gender": "FEMALE",
      "hairColor": "BLONDE",
      "hairLength": "SHORT",
      "eyeColor": "BLUE",
      "skinTone": "LIGHT",
      "hunger": 63.20000000000016,
      "tiredness": 21.19999999999996,
      "mood": 84.40000000000032,
      "hygiene": 71.59999999999968,
      "currentRoom": "APARTMENT",
      "inventoryItemTypes": []
    },
    {
      "id": "879417fb-79b9-4b1e-9a9a-468551c15fdd",
      "name": "Victoria",
      "gender": "FEMALE",
      "hairColor": "BLACK",
      "hairLength": "SHORT",
      "eyeColor": "BLUE",
      "skinTone": "LIGHT",
      "hunger": 62.90000000000016,
      "tiredness": 21.39999999999996,
      "mood": 99.20000000000005,
      "hygiene": 71.44999999999968,
      "currentRoom": "APARTMENT",
      "inventoryItemTypes": []
    },
    {
      "id": "d7a3bcdf-7988-49a4-84fa-99bc2cf38a72",
      "name": "frau nerz",
      "gender": "FEMALE",
      "hairColor": "BLONDE",
      "hairLength": "LONG",
      "eyeColor": "BLUE",
      "skinTone": "LIGHT",
      "hunger": 74.60000000000005,
      "tiredness": 13.599999999999987,
      "mood": 98.2000000000001,
      "hygiene": 77.2999999999999,
      "currentRoom": "APARTMENT",
      "inventoryItemTypes": []
    }
  ],
  "relationships": {
    "879417fb-79b9-4b1e-9a9a-468551c15fdd_b1972cad-1526-4557-a443-09289488dcbf": {
      "value": 0.0,
      "friends": false,
      "introduced": false,
      "romanticFeelings": false,
      "romanticRejected": false,
      "romanticAccepted": false,
      "avoidUntilTick": 0
    },
    "879417fb-79b9-4b1e-9a9a-468551c15fdd_d7a3bcdf-7988-49a4-84fa-99bc2cf38a72": {
      "value": 0.0,
      "friends": false,
      "introduced": true,
      "romanticFeelings": false,
      "romanticRejected": false,
      "romanticAccepted": false,
      "avoidUntilTick": 0
    }
  },
  "timeOfDay": "MORNING",
  "dayNightCycleMs": 27800,
  "gameTick": 278,
  "activeGlobalEvents": [
    "CONCERT",
    "BIRTHDAY",
    "DELIVERY"
  ],
  "tutorialCompleted": true,
  "fridgeFoodUnits": 20
}